LICENSE
README.md
setup.py
async_cats/__init__.py
async_cats/client.py
async_cats/http.py
async_cats/mixins/__init__.py
async_cats/mixins/base.py
async_cats/mixins/breeds.py
async_cats/mixins/categories.py
async_cats/mixins/favourites.py
async_cats/mixins/images.py
async_cats/mixins/votes.py
async_cats/utils/__init__.py
async_cats/utils/_dataclasses.py
async_cats/utils/constants.py
async_cats/utils/exceptions.py
async_cats/utils/validator.py
cats/__init__.py
cats/client.py
cats/http.py
cats.py.egg-info/PKG-INFO
cats.py.egg-info/SOURCES.txt
cats.py.egg-info/dependency_links.txt
cats.py.egg-info/requires.txt
cats.py.egg-info/top_level.txt
cats/mixins/__init__.py
cats/mixins/base.py
cats/mixins/breeds.py
cats/mixins/categories.py
cats/mixins/favourites.py
cats/mixins/images.py
cats/mixins/votes.py
cats/utils/__init__.py
cats/utils/_dataclasses.py
cats/utils/constants.py
cats/utils/exceptions.py
cats/utils/validator.py