Metadata-Version: 2.1
Name: cats.py
Version: 1.0.0
Summary: A synchronous, object oriented API wrapper for thecatapi
Home-page: https://github.com/MarzaElise/cats.py
Author: Marcus
License: GNU AGPLv3
Platform: UNKNOWN
Classifier: Intended Audience :: Developers
Classifier: Topic :: Software Development :: Build Tools
Classifier: Programming Language :: Python :: 3
Classifier: Programming Language :: Python :: 3.6
Classifier: Programming Language :: Python :: 3.7
Classifier: Programming Language :: Python :: 3.8
Classifier: Programming Language :: Python :: 3.9
License-File: LICENSE
